s3file/__init__.py
s3file/main.py
nextprotocol_s3file-0.1.2.dist-info/METADATA
nextprotocol_s3file-0.1.2.dist-info/WHEEL
nextprotocol_s3file-0.1.2.dist-info/licenses/LICENSE
nextprotocol_s3file-0.1.2.dist-info/RECORD
