Metadata-Version: 2.4
Name: NEXTProtocol_s3file
Version: 0.1.2
Summary: A package to upload files to S3
Author-email: Clapin Arthur <clapin.arthur@gmail.com>
License-Expression: MIT
License-File: LICENSE
Classifier: Operating System :: OS Independent
Classifier: Programming Language :: Python :: 3
Requires-Python: >=3.9
Requires-Dist: boto3>=1.26.0
